makeitsample/__init__.py
makeitsample/forest.py
makeitsample/language_family_tree.py
makeitsample/makeitsample.py
makeitsample-1.0.2.dist-info/licenses/LICENSE
makeitsample-1.0.2.dist-info/METADATA
makeitsample-1.0.2.dist-info/WHEEL
makeitsample-1.0.2.dist-info/entry_points.txt
makeitsample-1.0.2.dist-info/top_level.txt
makeitsample-1.0.2.dist-info/RECORD
