Metadata-Version: 2.4
Name: makeitsample
Version: 1.0.2
Summary: A Toolkit for Generating Typological Language Samples Based on the Diversity Value
Author-email: Luca Brigada Villa <luca.brigadavilla@unipv.it>
License-Expression: MIT
Project-URL: Homepage, https://github.com/unipv-larl/makeitsample
Project-URL: Issues, https://github.com/unipv-larl/makeitsample/issues
Keywords: linguistics,typology,language diversity,language sampling,diversity value,language families,phylogenetics,sampling
Classifier: Programming Language :: Python
Classifier: Programming Language :: Python :: 3
Classifier: Programming Language :: Python :: 3 :: Only
Classifier: Programming Language :: Python :: 3.6
Classifier: Programming Language :: Python :: 3.7
Classifier: Programming Language :: Python :: 3.8
Classifier: Programming Language :: Python :: 3.9
Classifier: Programming Language :: Python :: 3.10
Classifier: Programming Language :: Python :: 3.11
Classifier: Programming Language :: Python :: 3.12
Classifier: Operating System :: OS Independent
Requires-Python: >=3.6
License-File: LICENSE
Requires-Dist: pandas
Requires-Dist: networkx
Dynamic: license-file
